odoo10_addon_l10n_br_account-10.0.1.0.0.99.dev104-nspkg.pth
odoo/addons/l10n_br_account/README.rst
odoo/addons/l10n_br_account/__init__.py
odoo/addons/l10n_br_account/__manifest__.py
odoo/addons/l10n_br_account/data/l10n_br_account.cnae.csv
odoo/addons/l10n_br_account/data/l10n_br_account.fiscal.document.csv
odoo/addons/l10n_br_account/data/l10n_br_account.service.type.csv
odoo/addons/l10n_br_account/data/l10n_br_account_data.xml
odoo/addons/l10n_br_account/demo/base_demo.xml
odoo/addons/l10n_br_account/i18n/l10n_br_account.pot
odoo/addons/l10n_br_account/images/l10n_br-hover.png
odoo/addons/l10n_br_account/images/l10n_br.png
odoo/addons/l10n_br_account/migrations/8.0.1.0.1/openupgrade_analysis.txt
odoo/addons/l10n_br_account/migrations/8.0.1.0.1/openupgrade_analysis_work.txt
odoo/addons/l10n_br_account/models/__init__.py
odoo/addons/l10n_br_account/models/account_fiscal_position.py
odoo/addons/l10n_br_account/models/account_fiscal_position_abstract.py
odoo/addons/l10n_br_account/models/account_fiscal_position_rule.py
odoo/addons/l10n_br_account/models/account_fiscal_position_template.py
odoo/addons/l10n_br_account/models/account_invoice.py
odoo/addons/l10n_br_account/models/account_invoice_line.py
odoo/addons/l10n_br_account/models/account_journal.py
odoo/addons/l10n_br_account/models/account_move_line.py
odoo/addons/l10n_br_account/models/account_tax.py
odoo/addons/l10n_br_account/models/account_tax_template.py
odoo/addons/l10n_br_account/models/l10n_br_account.py
odoo/addons/l10n_br_account/models/l10n_br_account_cnae.py
odoo/addons/l10n_br_account/models/l10n_br_account_fiscal_category.py
odoo/addons/l10n_br_account/models/l10n_br_account_fiscal_document.py
odoo/addons/l10n_br_account/models/l10n_br_account_fiscal_document_serie.py
odoo/addons/l10n_br_account/models/l10n_br_account_fiscal_partner_type.py
odoo/addons/l10n_br_account/models/l10n_br_account_product_category.py
odoo/addons/l10n_br_account/models/l10n_br_account_service_type.py
odoo10_addon_l10n_br_account-10.0.1.0.0.99.dev104.dist-info/METADATA
odoo10_addon_l10n_br_account-10.0.1.0.0.99.dev104.dist-info/WHEEL
odoo10_addon_l10n_br_account-10.0.1.0.0.99.dev104.dist-info/namespace_packages.txt
odoo10_addon_l10n_br_account-10.0.1.0.0.99.dev104.dist-info/top_level.txt
odoo10_addon_l10n_br_account-10.0.1.0.0.99.dev104.dist-info/RECORD
