Metadata-Version: 2.1
Name: odoo10-addon-l10n-br-account
Version: 10.0.1.0.0.99.dev104
Summary: Brazilian Localization Account
Home-page: http://odoobrasil.org
Author: Akretion, Odoo Community Association (OCA)
Author-email: support@odoo-community.org
License: AGPL-3
Platform: UNKNOWN
Classifier: Programming Language :: Python
Classifier: Framework :: Odoo
Classifier: License :: OSI Approved :: GNU Affero General Public License v3
Requires-Python: ~=2.7
Requires-Dist: odoo10-addon-account-fiscal-position-rule
Requires-Dist: odoo10-addon-l10n-br-base
Requires-Dist: odoo10-addon-l10n-br-generic
Requires-Dist: odoo (<10.1dev,>=10.0)
